sagar_nueron_gpt2/.gitignore
sagar_nueron_gpt2/README.md
sagar_nueron_gpt2/TrainAndSaveGptWeights.py
sagar_nueron_gpt2/__init__.py
sagar_nueron_gpt2/docs.txt
sagar_nueron_gpt2/inference_model.py
sagar_nueron_gpt2/pyproject.toml
sagar_nueron_gpt2/requirements.txt
sagar_nueron_gpt2/requirements_cpu.txt
sagar_nueron_gpt2/load_model/load_local_models.py
sagar_nueron_gpt2/load_model/loading_model_orignal_gpt.py
sagar_nueron_gpt2/model_configuration/__init__.py
sagar_nueron_gpt2/model_configuration/gpt_model.py
sagar_nueron_gpt2/processing/Text2TokenViceVersa.py
sagar_nueron_gpt2/processing/__init__.py
sagar_nueron_gpt2/processing/data_loader_train_val.py
sagar_nueron_gpt2/processing/loss_calculate.py
sagar_nueron_gpt2/processing/save_load_weights.py
sagar_nueron_gpt2/transfomer/__init__.py
sagar_nueron_gpt2/transfomer/feed_forward_NN.py
sagar_nueron_gpt2/transfomer/gelu.py
sagar_nueron_gpt2/transfomer/layer_norm.py
sagar_nueron_gpt2/transfomer/masked_mutlihead_attention.py
sagar_nueron_gpt2/transfomer/transformer_architecture.py
sagar_nueron_gpt2-0.1.8.dist-info/METADATA
sagar_nueron_gpt2-0.1.8.dist-info/WHEEL
sagar_nueron_gpt2-0.1.8.dist-info/RECORD
