Metadata-Version: 2.4
Name: sagar_nueron_gpt2
Version: 0.1.8
Summary: A GPT-2 implementation for training and inference in pytorch
Project-URL: Homepage, https://github.com/Gangasagarhl/SAGAR_NUERON/tree/main/GPT2
Project-URL: Source, https://github.com/Gangasagarhl/SAGAR_NUERON
Author-email: GANGASAGAR HL <hlgsagar.1@gmail.com>
License-Expression: MIT
Keywords: gpt2,machine learning,nlp
Classifier: License :: OSI Approved :: MIT License
Classifier: Operating System :: OS Independent
Classifier: Programming Language :: Python :: 3
Requires-Python: >=3.8
Provides-Extra: ml
Requires-Dist: tiktoken; extra == 'ml'
Requires-Dist: torch; extra == 'ml'
